{
  "generated_at": "2026-05-08T20:15:47.533253+00:00",
  "summary": {
    "total": 2,
    "healthy": 0,
    "unhealthy": 2,
    "avg_response_ms": 1005
  },
  "urls": [
    {
      "name": "Ndevu Store Application",
      "url": "https://ndevu-store-be.onrender.com",
      "dns_ms": 3,
      "healthy": false,
      "status_code": null,
      "response_ms": null,
      "uptime_30d_pct": 0.0,
      "last_checked": "2026-05-08T20:15:29.740318+00:00"
    },
    {
      "name": "The Inventory Application",
      "url": "https://the-inventory-hazel.vercel.app",
      "dns_ms": 21,
      "healthy": false,
      "status_code": 200,
      "response_ms": 1005,
      "uptime_30d_pct": 0.0,
      "last_checked": "2026-05-08T20:15:29.782101+00:00"
    }
  ]
}